_libCombineArrays.abi3.so
combineArrays.py
combineArrays-0.77.dist-info/LICENSE
combineArrays-0.77.dist-info/METADATA
combineArrays-0.77.dist-info/WHEEL
combineArrays-0.77.dist-info/top_level.txt
combineArrays-0.77.dist-info/RECORD
