Metadata-Version: 2.1
Name: combineArrays
Version: 0.77
Summary: Using Python CFFI bindings for funtions to combine NumPy arrays in C++
Home-page: UNKNOWN
Author: Norbert Henseler
Author-email: nhenseler@web.de
License: UNKNOWN
Platform: UNKNOWN
License-File: LICENSE
Requires-Dist: cffi (>=1.0.0)
